ltfte/__init__.py
ltfte/augbondcurve.py
ltfte/dispconvoting.py
ltfte/tech.py
ltfte/dao2dao/__init__.py
ltfte/dao2dao/proposal_inverter.py
ltfte/dao2dao/test_broker.py
ltfte/tokenengi/__init__.py
ltfte/tokenengi/bondingcurves.py
ltfte/tokenengi/qia.py
ltfte/tokenengi/swengi.py
ltfte-0.0.2.dist-info/LICENSE
ltfte-0.0.2.dist-info/METADATA
ltfte-0.0.2.dist-info/WHEEL
ltfte-0.0.2.dist-info/top_level.txt
ltfte-0.0.2.dist-info/RECORD
